setup.cfg
setup.py
Azimuth.egg-info/PKG-INFO
Azimuth.egg-info/SOURCES.txt
Azimuth.egg-info/dependency_links.txt
Azimuth.egg-info/requires.txt
Azimuth.egg-info/top_level.txt
azimuth/__init__.py
azimuth/cli_run_model.py
azimuth/cluster_job.py
azimuth/corrstats.py
azimuth/load_data.py
azimuth/local_multiprocessing.py
azimuth/metrics.py
azimuth/model_comparison.py
azimuth/predict.py
azimuth/util.py
azimuth/features/__init__.py
azimuth/features/featurization.py
azimuth/features/featurization.py.BACKUP.24184.py
azimuth/features/featurization.py.BASE.24184.py
azimuth/features/featurization.py.LOCAL.24184.py
azimuth/features/featurization.py.REMOTE.24184.py
azimuth/features/microhomology.py
azimuth/models/DNN.py
azimuth/models/GP.py
azimuth/models/__init__.py
azimuth/models/baselines.py
azimuth/models/ensembles.py
azimuth/models/gpy_ssk.py
azimuth/models/regression.py
azimuth/models/ssk.py
azimuth/saved_models/V3_model_full.pickle
azimuth/saved_models/V3_model_nopos.pickle
azimuth/saved_models/V3_model_nopos_azure.pickle
azimuth/tests/__init__.py
azimuth/tests/test_saved_models.py