Metadata-Version: 1.0
Name: Azimuth
Version: 2.0
Summary: Machine Learning-Based Predictive Modelling of CRISPR/Cas9 guide efficiency
Home-page: UNKNOWN
Author: Nicolo Fusi and Jennifer Listgarten
Author-email: fusi@microsoft.com, jennl@microsoft.com
License: BSD
Platform: UNKNOWN
